sketchnu/__init__.py
sketchnu/countmin.py
sketchnu/hashes.py
sketchnu/heavyhitters.py
sketchnu/helpers.py
sketchnu/hll_bias_experiment.py
sketchnu/hll_constants.py
sketchnu/hyperloglog.py
tests/__init__.py
tests/test_countmin.py
tests/test_hashes.py
tests/test_heavyhitters.py
tests/test_helpers.py
tests/test_hyperloglog.py
tests/zipf.py
sketchnu-1.4.0.dist-info/LICENSE
sketchnu-1.4.0.dist-info/METADATA
sketchnu-1.4.0.dist-info/WHEEL
sketchnu-1.4.0.dist-info/top_level.txt
sketchnu-1.4.0.dist-info/RECORD
